<?xml version="1.0" encoding="UTF-8"?>
<tv generator-info-name="WebGrab+Plus/w MDB &amp; REX Postprocess -- version V3.2.1.0 -- Jan van Straaten" generator-info-url="http://www.webgrabplus.com">
  <channel id="vtvcab3">
    <display-name lang="vi">VTVcab 3</display-name>
    <url>http://www.tv24.vn</url>
  </channel>
  <channel id="vtvcab4">
    <display-name lang="vi">VTVcab 4</display-name>
    <url>http://www.tv24.vn</url>
  </channel>
  <channel id="vtvcab5">
    <display-name lang="vi">VTVcab 5</display-name>
    <url>http://www.tv24.vn</url>
  </channel>
  <channel id="vtvcab6">
    <display-name lang="vi">VTVcab 6</display-name>
    <url>http://www.tv24.vn</url>
  </channel>
  <channel id="vtvcab7">
    <display-name lang="vi">VTVcab 7</display-name>
    <url>http://www.tv24.vn</url>
  </channel>
  <channel id="vtvcab8">
    <display-name lang="vi">VTVcab 8</display-name>
    <url>http://www.tv24.vn</url>
  </channel>
  <channel id="vtvcab9">
    <display-name lang="vi">VTVcab 9</display-name>
    <url>http://www.tv24.vn</url>
  </channel>
  <channel id="vtvcab11">
    <display-name lang="vi">VTVCab11</display-name>
    <url>http://www.tv24.vn</url>
  </channel>
  <channel id="woman">
    <display-name lang="vi">Woman</display-name>
    <url>http://www.tv24.vn</url>
  </channel>
  <programme start="20210912060000 +0700" stop="20210912061500 +0700" channel="vtvcab3">
    <title lang="vi">Bản tin Thế giới thể thao ( 6H) Live</title>
  </programme>
  <programme start="20210912061500 +0700" stop="20210912081500 +0700" channel="vtvcab3">
    <title lang="vi">US Open 2021 Ngày 12 Bán kết 1 đơn nam Fox 1 Phát lại</title>
  </programme>
  <programme start="20210912081500 +0700" stop="20210912101500 +0700" channel="vtvcab3">
    <title lang="vi">US Open 2021 Ngày 12 Chung kết đôi nam Fox 1 Phát lại</title>
  </programme>
  <programme start="20210912101500 +0700" stop="20210912103000 +0700" channel="vtvcab3">
    <title lang="vi">Thể thao &amp; Thời tiết</title>
  </programme>
  <programme start="20210912103000 +0700" stop="20210912110000 +0700" channel="vtvcab3">
    <title lang="vi">Tạp chí Cầu lông 36-21 Mới</title>
  </programme>
  <programme start="20210912110000 +0700" stop="20210912113000 +0700" channel="vtvcab3">
    <title lang="vi">Mổ băng Quần vợt 2021 Preview Chung kết US Open</title>
  </programme>
  <programme start="20210912113000 +0700" stop="20210912114500 +0700" channel="vtvcab3">
    <title lang="vi">Bản tin Thể thao Việt Nam 11H30 Live</title>
  </programme>
  <programme start="20210912114500 +0700" stop="20210912120000 +0700" channel="vtvcab3">
    <title lang="vi">Bản tin Thế giới thể thao ( 6H) Phát lại</title>
  </programme>
  <programme start="20210912120000 +0700" stop="20210912121500 +0700" channel="vtvcab3">
    <title lang="vi">Bản tin Golfing World Phát lại</title>
  </programme>
  <programme start="20210912121500 +0700" stop="20210912143000 +0700" channel="vtvcab3">
    <title lang="vi">US Open 2021 Ngày 13 Chung kết nữ Fox 1 Phát lại</title>
  </programme>
  <programme start="20210912143000 +0700" stop="20210912150000 +0700" channel="vtvcab3">
    <title lang="vi">Tạp chí Cầu lông 36-21</title>
  </programme>
  <programme start="20210912150000 +0700" stop="20210912151500 +0700" channel="vtvcab3">
    <title lang="vi">Bản tin Thế giới thể thao ( 6H) Phát lại</title>
  </programme>
  <programme start="20210912151500 +0700" stop="20210912153000 +0700" channel="vtvcab3">
    <title lang="vi">Bản tin Thể thao Việt Nam 11H30 Phát lại</title>
  </programme>
  <programme start="20210912153000 +0700" stop="20210912173000 +0700" channel="vtvcab3">
    <title lang="vi">US Open 2021 Ngày 13 Chung kết đôi nam nữ Fox 1 Phát lại</title>
  </programme>
  <programme start="20210912173000 +0700" stop="20210912180000 +0700" channel="vtvcab3">
    <title lang="vi">Ligue 1 show 36-21</title>
  </programme>
  <programme start="20210912180000 +0700" stop="20210912200000 +0700" channel="vtvcab3">
    <title lang="vi">Hạng Nhất Pháp 21/22 Vòng 5 Montpellier vs Saint-Etienne Trực tiếp</title>
  </programme>
  <programme start="20210912200000 +0700" stop="20210912220000 +0700" channel="vtvcab3">
    <title lang="vi">VĐQG Italia - Serie A 21/22 Vòng 3 Cagliari vs Genoa Trực tiếp</title>
  </programme>
  <programme start="20210912000000 +0700" stop="20210912005500 +0700" channel="vtvcab4">
    <title lang="vi">Nhà Tù Thần Tượng\r\nTập 10</title>
  </programme>
  <programme start="20210912005500 +0700" stop="20210912010000 +0700" channel="vtvcab4">
    <title lang="vi">Mâm Nhà Food Club\r\nBánh Nhúng Tuổi Thơ Giòn Tan</title>
  </programme>
  <programme start="20210912010000 +0700" stop="20210912020000 +0700" channel="vtvcab4">
    <title lang="vi">Tạp Chí Giải Trí (Tò Mò Showbiz)\r\nSố 64</title>
  </programme>
  <programme start="20210912020000 +0700" stop="20210912030000 +0700" channel="vtvcab4">
    <title lang="vi">Nhà Tù Thần Tượng\r\nTập 7</title>
  </programme>
  <programme start="20210912030000 +0700" stop="20210912040000 +0700" channel="vtvcab4">
    <title lang="vi">Tạp Chí Giải Trí (Tò Mò Showbiz)\r\nSố 65</title>
  </programme>
  <programme start="20210912040000 +0700" stop="20210912051000 +0700" channel="vtvcab4">
    <title lang="vi">Nhà Tù Thần Tượng\r\nTập 8</title>
  </programme>
  <programme start="20210912051000 +0700" stop="20210912060000 +0700" channel="vtvcab4">
    <title lang="vi">Tạp Chí Giải Trí (Tò Mò Showbiz)\r\nSố 66</title>
  </programme>
  <programme start="20210912060000 +0700" stop="20210912070000 +0700" channel="vtvcab4">
    <title lang="vi">Tạp Chí Giải Trí (Tò Mò Showbiz)\r\nSố 62</title>
  </programme>
  <programme start="20210912070000 +0700" stop="20210912074500 +0700" channel="vtvcab4">
    <title lang="vi">Nhà Tù Thần Tượng\r\nTập 7</title>
  </programme>
  <programme start="20210912074500 +0700" stop="20210912080000 +0700" channel="vtvcab4">
    <title lang="vi">Mâm Nhà Food Club\r\nBánh Nhúng Tuổi Thơ Giòn Tan</title>
  </programme>
  <programme start="20210912080000 +0700" stop="20210912090000 +0700" channel="vtvcab4">
    <title lang="vi">Tạp Chí Giải Trí (Tò Mò Showbiz)\r\nSố 63</title>
  </programme>
  <programme start="20210912090000 +0700" stop="20210912095500 +0700" channel="vtvcab4">
    <title lang="vi">Nhà Tù Thần Tượng\r\nTập 10</title>
  </programme>
  <programme start="20210912095500 +0700" stop="20210912100000 +0700" channel="vtvcab4">
    <title lang="vi">Mâm Nhà Food Club\r\n2 Cách Chế Biến Cá Hồi Với Bơ Tươi</title>
  </programme>
  <programme start="20210912100000 +0700" stop="20210912134500 +0700" channel="vtvcab4">
    <title lang="vi">Phim Truyện Phát Lại\r\nThư Ký Kim Sao Thế Từ Tập 15 Đến Tập 19</title>
  </programme>
  <programme start="20210912134500 +0700" stop="20210912150000 +0700" channel="vtvcab4">
    <title lang="vi">Tạp Chí Giải Trí (Tò Mò Showbiz)\r\nSố 66</title>
  </programme>
  <programme start="20210912150000 +0700" stop="20210912190000 +0700" channel="vtvcab4">
    <title lang="vi">Phim Truyện Phát Lại\r\n\r\n\r\n\r\nCửu Châu Hải Thượng Mục Vân Ký Từ Tập 24 Đến Tập 28</title>
  </programme>
  <programme start="20210912190000 +0700" stop="20210912200000 +0700" channel="vtvcab4">
    <title lang="vi">Tạp Chí Giải Trí (Tò Mò Showbiz)\r\nSố 63</title>
  </programme>
  <programme start="20210912200000 +0700" stop="20210912204500 +0700" channel="vtvcab4">
    <title lang="vi">Tạp Chí Giải Trí (Tò Mò Showbiz)\r\nSố 7 P1 + 77</title>
  </programme>
  <programme start="20210912204500 +0700" stop="20210912224500 +0700" channel="vtvcab4">
    <title lang="vi">Phim Điện Ảnh\r\nSiêu Mèo</title>
  </programme>
  <programme start="20210912000000 +0700" stop="20210912010000 +0700" channel="vtvcab5">
    <title lang="vi">E Nhạc Phim</title>
  </programme>
  <programme start="20210912010000 +0700" stop="20210912020000 +0700" channel="vtvcab5">
    <title lang="vi">Nghìn Lẻ Một Chuyện</title>
  </programme>
  <programme start="20210912020000 +0700" stop="20210912030000 +0700" channel="vtvcab5">
    <title lang="vi">Lữ Khách 24h</title>
  </programme>
  <programme start="20210912030000 +0700" stop="20210912040000 +0700" channel="vtvcab5">
    <title lang="vi">Cha Con Hợp Sức</title>
  </programme>
  <programme start="20210912040000 +0700" stop="20210912050000 +0700" channel="vtvcab5">
    <title lang="vi">Sóng Nhạc</title>
  </programme>
  <programme start="20210912050000 +0700" stop="20210912060000 +0700" channel="vtvcab5">
    <title lang="vi">Bolero/Sân Khấu Truyền Thống</title>
  </programme>
  <programme start="20210912060000 +0700" stop="20210912070000 +0700" channel="vtvcab5">
    <title lang="vi">E Nhạc Phim</title>
  </programme>
  <programme start="20210912070000 +0700" stop="20210912080000 +0700" channel="vtvcab5">
    <title lang="vi">Nghìn Lẻ Một Chuyện</title>
  </programme>
  <programme start="20210912080000 +0700" stop="20210912090000 +0700" channel="vtvcab5">
    <title lang="vi">Du Lịch Kỳ Thú</title>
  </programme>
  <programme start="20210912090000 +0700" stop="20210912100000 +0700" channel="vtvcab5">
    <title lang="vi">CON CỦA NGƯỜI HẦU GÁI Phần 3 - Tập 473</title>
  </programme>
  <programme start="20210912100000 +0700" stop="20210912110000 +0700" channel="vtvcab5">
    <title lang="vi">Pháo Hoa Sông Đây Mưa Sông Đó Tập 03</title>
  </programme>
  <programme start="20210912110000 +0700" stop="20210912120000 +0700" channel="vtvcab5">
    <title lang="vi">Truyền Thuyết Liêu Trai (35T) Tập 11</title>
  </programme>
  <programme start="20210912120000 +0700" stop="20210912130000 +0700" channel="vtvcab5">
    <title lang="vi">Kẻ Giấu Mặt (36T) Tập 25</title>
  </programme>
  <programme start="20210912130000 +0700" stop="20210912140000 +0700" channel="vtvcab5">
    <title lang="vi">Trả Lại Thế Giới Cho Em (61T) Tập 20</title>
  </programme>
  <programme start="20210912140000 +0700" stop="20210912150000 +0700" channel="vtvcab5">
    <title lang="vi">CON CỦA NGƯỜI HẦU GÁI Phần 3 - Tập 473</title>
  </programme>
  <programme start="20210912150000 +0700" stop="20210912160000 +0700" channel="vtvcab5">
    <title lang="vi">Cha Con Hợp Sức</title>
  </programme>
  <programme start="20210912160000 +0700" stop="20210912170000 +0700" channel="vtvcab5">
    <title lang="vi">Sóng Nhạc</title>
  </programme>
  <programme start="20210912170000 +0700" stop="20210912180000 +0700" channel="vtvcab5">
    <title lang="vi">Phim TVB - Tây Du Ký (Phần 2) Tập 39</title>
  </programme>
  <programme start="20210912180000 +0700" stop="20210912190000 +0700" channel="vtvcab5">
    <title lang="vi">Phim TVB - Tây Du Ký (Phần 2) Tập 39</title>
  </programme>
  <programme start="20210912190000 +0700" stop="20210912200000 +0700" channel="vtvcab5">
    <title lang="vi">Truyền Thuyết Liêu Trai (35T) Tập 12</title>
  </programme>
  <programme start="20210912200000 +0700" stop="20210912210000 +0700" channel="vtvcab5">
    <title lang="vi">Trả Lại Thế Giới Cho Em (61T) Tập 21</title>
  </programme>
  <programme start="20210912210000 +0700" stop="20210912220000 +0700" channel="vtvcab5">
    <title lang="vi">Pháo Hoa Sông Đây Mưa Sông Đó Tập 04</title>
  </programme>
  <programme start="20210912220000 +0700" stop="20210912230000 +0700" channel="vtvcab5">
    <title lang="vi">CON CỦA NGƯỜI HẦU GÁI Phần 3 - Tập 474</title>
  </programme>
  <programme start="20210912000000 +0700" stop="20210912010000 +0700" channel="vtvcab6">
    <title lang="vi">Juventus TRỰC TIẾP BQ BLV: DB</title>
  </programme>
  <programme start="20210912010000 +0700" stop="20210912013000 +0700" channel="vtvcab6">
    <title lang="vi">Gameshow 3F Số 12</title>
  </programme>
  <programme start="20210912013000 +0700" stop="20210912014500 +0700" channel="vtvcab6">
    <title lang="vi">TRICK SHOT GOLF BATTLE 03 - 20</title>
  </programme>
  <programme start="20210912014500 +0700" stop="20210912020000 +0700" channel="vtvcab6">
    <title lang="vi">ATP World - Agassi &amp; Sampras</title>
  </programme>
  <programme start="20210912020000 +0700" stop="20210912040000 +0700" channel="vtvcab6">
    <title lang="vi">Hạng Nhất Pháp 21/22 Vòng 5 Monaco vs Marseille TRỰC TIẾP BQ BLV: DB</title>
  </programme>
  <programme start="20210912040000 +0700" stop="20210912041500 +0700" channel="vtvcab6">
    <title lang="vi">Trận đấu 10 phút: Phát lại BWF Yonex All England Open 2021 Vòng 2 đơn nam Kento</title>
  </programme>
  <programme start="20210912041500 +0700" stop="20210912043000 +0700" channel="vtvcab6">
    <title lang="vi">Lương Xuân Trường và IRC</title>
  </programme>
  <programme start="20210912043000 +0700" stop="20210912044500 +0700" channel="vtvcab6">
    <title lang="vi">Trận đấu 10 phút: PHÁT LẠI NBA 2020/21- Hành trình vô địch Game 114: Milwaukee</title>
  </programme>
  <programme start="20210912044500 +0700" stop="20210912054500 +0700" channel="vtvcab6">
    <title lang="vi">Khu vực Châu Âu Khu vực Châu Âu Highlight Full Lượt 5</title>
  </programme>
  <programme start="20210912054500 +0700" stop="20210912060000 +0700" channel="vtvcab6">
    <title lang="vi">GW - Stenson &amp; Dominica</title>
  </programme>
  <programme start="20210912060000 +0700" stop="20210912080000 +0700" channel="vtvcab6">
    <title lang="vi">Hạng Nhất Pháp 21/22 Vòng 5 Monaco vs Marseille PHÁT LẠI BLV: DB</title>
  </programme>
  <programme start="20210912080000 +0700" stop="20210912090000 +0700" channel="vtvcab6">
    <title lang="vi">Tạp chí Vòng loại World Cup 2022 Khu vực Châu Âu Highlight Lượt trận 6</title>
  </programme>
  <programme start="20210912090000 +0700" stop="20210912101500 +0700" channel="vtvcab6">
    <title lang="vi">ATP World - Top 10 Djokovic Phim Olympic Tokyo 2020 Ánh sáng đoàn kết</title>
  </programme>
  <programme start="20210912101500 +0700" stop="20210912104500 +0700" channel="vtvcab6">
    <title lang="vi">Gamesshow 3F Số 7</title>
  </programme>
  <programme start="20210912104500 +0700" stop="20210912110000 +0700" channel="vtvcab6">
    <title lang="vi">Bản tin On Sports TRƯA - 8 phút - Mới TRỰC TIẾP</title>
  </programme>
  <programme start="20210912110000 +0700" stop="20210912114500 +0700" channel="vtvcab6">
    <title lang="vi">Lục Trinh Truyền kỳ (45T) Tập 15</title>
  </programme>
  <programme start="20210912114500 +0700" stop="20210912120000 +0700" channel="vtvcab6">
    <title lang="vi">Trận đấu 10 phút: Phát lại BWF Yonex All England Open 2021 Tứ kết đơn nam Viktor</title>
  </programme>
  <programme start="20210912120000 +0700" stop="20210912121500 +0700" channel="vtvcab6">
    <title lang="vi">Bản tin On Sports TRƯA - 8 phút ( P lại)</title>
  </programme>
  <programme start="20210912121500 +0700" stop="20210912130000 +0700" channel="vtvcab6">
    <title lang="vi">Yêu lại từ đầu (33T) Tập 20</title>
  </programme>
  <programme start="20210912130000 +0700" stop="20210912131500 +0700" channel="vtvcab6">
    <title lang="vi">Bản tin On Sports TRƯA - 8 phút ( P lại)</title>
  </programme>
  <programme start="20210912131500 +0700" stop="20210912133000 +0700" channel="vtvcab6">
    <title lang="vi">Trận đấu 10 phút: Phát lại Copa America 2021- Chung kết: Argentina - Brasil</title>
  </programme>
  <programme start="20210912133000 +0700" stop="20210912140000 +0700" channel="vtvcab6">
    <title lang="vi">Bundesliga Weekly 36-21 Mới</title>
  </programme>
  <programme start="20210912140000 +0700" stop="20210912143000 +0700" channel="vtvcab6">
    <title lang="vi">Ligue 1 show 36-21 Mới</title>
  </programme>
  <programme start="20210912143000 +0700" stop="20210912150000 +0700" channel="vtvcab6">
    <title lang="vi">LUXURY LIFE STYLE - Số 24 - Phát lại Khám phá quá trình dát vàng căn penhouse ở</title>
  </programme>
  <programme start="20210912150000 +0700" stop="20210912151500 +0700" channel="vtvcab6">
    <title lang="vi">Ca nhạc Vmusic ( P lại) Số 62</title>
  </programme>
  <programme start="20210912151500 +0700" stop="20210912153000 +0700" channel="vtvcab6">
    <title lang="vi">Soccers Skills số 3 15-20</title>
  </programme>
  <programme start="20210912153000 +0700" stop="20210912154500 +0700" channel="vtvcab6">
    <title lang="vi">Bản tin On Sports TRƯA - 8 phút ( P lại)</title>
  </programme>
  <programme start="20210912154500 +0700" stop="20210912163000 +0700" channel="vtvcab6">
    <title lang="vi">Yêu lại từ đầu (33T) Tập 20</title>
  </programme>
  <programme start="20210912163000 +0700" stop="20210912164500 +0700" channel="vtvcab6">
    <title lang="vi">GW - Stenson &amp; Dominica</title>
  </programme>
  <programme start="20210912164500 +0700" stop="20210912170000 +0700" channel="vtvcab6">
    <title lang="vi">Trận đấu 10 phút: Mới US Open- Bán kết 1 đơn nam: ... vs ..</title>
  </programme>
  <programme start="20210912170000 +0700" stop="20210912173000 +0700" channel="vtvcab6">
    <title lang="vi">Serie A Show 36-21 Mới</title>
  </programme>
  <programme start="20210912173000 +0700" stop="20210912174500 +0700" channel="vtvcab6">
    <title lang="vi">Ca nhạc Vmusic ( P lại) Số 62</title>
  </programme>
  <programme start="20210912174500 +0700" stop="20210912181500 +0700" channel="vtvcab6">
    <title lang="vi">Ligue 1 show 36-21</title>
  </programme>
  <programme start="20210912181500 +0700" stop="20210912184500 +0700" channel="vtvcab6">
    <title lang="vi">LUXURY LIFE STYLE - Số 24 - Phát lại Khám phá quá trình dát vàng căn penhouse ở</title>
  </programme>
  <programme start="20210912184500 +0700" stop="20210912190000 +0700" channel="vtvcab6">
    <title lang="vi">Trận đấu 10 phút: Phát lại BWF Yonex All England Open 2021 Vòng 2 đơn nam Kento</title>
  </programme>
  <programme start="20210912190000 +0700" stop="20210912191500 +0700" channel="vtvcab6">
    <title lang="vi">Bản tin On Sports TRƯA - 8 phút ( P lại)</title>
  </programme>
  <programme start="20210912191500 +0700" stop="20210912200000 +0700" channel="vtvcab6">
    <title lang="vi">Lục Trinh Truyền kỳ (45T) Tập 16</title>
  </programme>
  <programme start="20210912200000 +0700" stop="20210912203000 +0700" channel="vtvcab6">
    <title lang="vi">Ca nhạc Vmusic Mới Số 63</title>
  </programme>
  <programme start="20210912203000 +0700" stop="20210912223000 +0700" channel="vtvcab6">
    <title lang="vi">VĐQG Đức 21/22 Vòng 4 Eintracht Frankfurt vs Stuttgart TRỰC TIẾP BQ BLV: DB</title>
  </programme>
  <programme start="20210912000000 +0700" stop="20210912010000 +0700" channel="vtvcab7">
    <title lang="vi">Yoga 90</title>
  </programme>
  <programme start="20210912010000 +0700" stop="20210912011500 +0700" channel="vtvcab7">
    <title lang="vi">Cảnh Báo Tội Phạm 0609 Cướp xe máy của công nhân vệ sinh (Mới SX)</title>
  </programme>
  <programme start="20210912011500 +0700" stop="20210912013000 +0700" channel="vtvcab7">
    <title lang="vi">Làng Nghề Việt(104) 66</title>
  </programme>
  <programme start="20210912013000 +0700" stop="20210912020000 +0700" channel="vtvcab7">
    <title lang="vi">Nghệ Sỹ: Chuyện Đời- Chuyện Nghề (52) 0409 NSUT Mỹ Uyên</title>
  </programme>
  <programme start="20210912020000 +0700" stop="20210912023000 +0700" channel="vtvcab7">
    <title lang="vi">Bệnh Khó Nói 0409 Hương vùng kín</title>
  </programme>
  <programme start="20210912023000 +0700" stop="20210912030000 +0700" channel="vtvcab7">
    <title lang="vi">Tạp Chí Học Đường 24/7 40 (MỚI SX)</title>
  </programme>
  <programme start="20210912030000 +0700" stop="20210912040000 +0700" channel="vtvcab7">
    <title lang="vi">Music Like 0709 Yêu để cưới (Mới SX)</title>
  </programme>
  <programme start="20210912040000 +0700" stop="20210912044500 +0700" channel="vtvcab7">
    <title lang="vi">Phim Truyện (Pl18H30) Ngọt ngào tình cha (70)</title>
  </programme>
  <programme start="20210912044500 +0700" stop="20210912050000 +0700" channel="vtvcab7">
    <title lang="vi">Du Lịch Xanh(104) 85</title>
  </programme>
  <programme start="20210912050000 +0700" stop="20210912060000 +0700" channel="vtvcab7">
    <title lang="vi">Yoga 91</title>
  </programme>
  <programme start="20210912060000 +0700" stop="20210912063000 +0700" channel="vtvcab7">
    <title lang="vi">Tạp Chí Học Đường 24/7 40 (MỚI SX)</title>
  </programme>
  <programme start="20210912063000 +0700" stop="20210912070000 +0700" channel="vtvcab7">
    <title lang="vi">Cảnh Báo Đỏ 2408 Cách ly - từ quy định đến ý thức (MỚI SX)</title>
  </programme>
  <programme start="20210912070000 +0700" stop="20210912074500 +0700" channel="vtvcab7">
    <title lang="vi">Phim Truyện (Pl12H00) Siêu gián điệp (8) 6</title>
  </programme>
  <programme start="20210912074500 +0700" stop="20210912080000 +0700" channel="vtvcab7">
    <title lang="vi">Sk&amp;Cs 24/7 11/09/2021 12:00:00 SA</title>
  </programme>
  <programme start="20210912080000 +0700" stop="20210912083000 +0700" channel="vtvcab7">
    <title lang="vi">Cảnh Báo Từ Cuộc Sống 2808 Nghề chăm sóc thú cưng: Kiếm tiền không dễ</title>
  </programme>
  <programme start="20210912083000 +0700" stop="20210912090000 +0700" channel="vtvcab7">
    <title lang="vi">Nghệ Sỹ: Chuyện Đời, Chuyện Nghề 1109 NSUT Minh Hạnh</title>
  </programme>
  <programme start="20210912090000 +0700" stop="20210912094500 +0700" channel="vtvcab7">
    <title lang="vi">V Music 55</title>
  </programme>
  <programme start="20210912094500 +0700" stop="20210912100000 +0700" channel="vtvcab7">
    <title lang="vi">Công Sở Truyền Kỳ (210) 58</title>
  </programme>
  <programme start="20210912100000 +0700" stop="20210912103000 +0700" channel="vtvcab7">
    <title lang="vi">Blouse Trắng 2108 Đồng hành đẩy lùi dịch bệnh (MÓI SX)</title>
  </programme>
  <programme start="20210912103000 +0700" stop="20210912110000 +0700" channel="vtvcab7">
    <title lang="vi">Các Vấn Đề Y Tế 0609 Xu hướng gia tăng sử dụng thuốc lá điện tử và nung nóng ở t</title>
  </programme>
  <programme start="20210912110000 +0700" stop="20210912120000 +0700" channel="vtvcab7">
    <title lang="vi">Dj Star 2020 4</title>
  </programme>
  <programme start="20210912120000 +0700" stop="20210912124500 +0700" channel="vtvcab7">
    <title lang="vi">Phim Truyện 12H00 (Pm) Siêu gián điệp (8) 7</title>
  </programme>
  <programme start="20210912124500 +0700" stop="20210912133000 +0700" channel="vtvcab7">
    <title lang="vi">Phim Truyện (Pl 17H) Sông dài (39)</title>
  </programme>
  <programme start="20210912133000 +0700" stop="20210912140000 +0700" channel="vtvcab7">
    <title lang="vi">Alo 115 1808 Làm gì khi trẻ bị sốt cao, co giật? (MỚI SX)</title>
  </programme>
  <programme start="20210912140000 +0700" stop="20210912150000 +0700" channel="vtvcab7">
    <title lang="vi">Music Like 1109 Chuyện hẹn hò (Mới SX)</title>
  </programme>
  <programme start="20210912150000 +0700" stop="20210912160000 +0700" channel="vtvcab7">
    <title lang="vi">Phim Truyện (Pl 18H30) Ngọt ngào tình cha (70)</title>
  </programme>
  <programme start="20210912160000 +0700" stop="20210912161500 +0700" channel="vtvcab7">
    <title lang="vi">Cảnh Báo Từ Cuộc Sống 0909 Nỗi buồn nhập cư tại các đô thị lớn</title>
  </programme>
  <programme start="20210912161500 +0700" stop="20210912163000 +0700" channel="vtvcab7">
    <title lang="vi">Camera On 1009 Từ thiện mùa dịch - Khó hay dễ (Mới SX)</title>
  </programme>
  <programme start="20210912163000 +0700" stop="20210912170000 +0700" channel="vtvcab7">
    <title lang="vi">V Healthy 2608 Luyện tập tại nhà mùa dịch (MỚI SX)</title>
  </programme>
  <programme start="20210912170000 +0700" stop="20210912174500 +0700" channel="vtvcab7">
    <title lang="vi">Phim Truyện 17H00 Sông dài (39)</title>
  </programme>
  <programme start="20210912174500 +0700" stop="20210912180000 +0700" channel="vtvcab7">
    <title lang="vi">Du Lịch Xanh(104) 86</title>
  </programme>
  <programme start="20210912180000 +0700" stop="20210912183000 +0700" channel="vtvcab7">
    <title lang="vi">Căn Phòng Bí Mật 1209 Diễn viên Lưu Đê Ly (Mới SX)</title>
  </programme>
  <programme start="20210912183000 +0700" stop="20210912191500 +0700" channel="vtvcab7">
    <title lang="vi">Phim Truyện 18H30 (Pm) Ngọt ngào tình cha (70)</title>
  </programme>
  <programme start="20210912191500 +0700" stop="20210912194500 +0700" channel="vtvcab7">
    <title lang="vi">Các Vấn Đề Y Tế 0609 Xu hướng gia tăng sử dụng thuốc lá điện tử và nung nóng ở t</title>
  </programme>
  <programme start="20210912194500 +0700" stop="20210912200000 +0700" channel="vtvcab7">
    <title lang="vi">Sk&amp;Cs 24/7 12/09/2021 12:00:00 SA</title>
  </programme>
  <programme start="20210912200000 +0700" stop="20210912203000 +0700" channel="vtvcab7">
    <title lang="vi">Truy Vết 1209 Củ Bình Vôi trên núi cao (Mới SX)</title>
  </programme>
  <programme start="20210912203000 +0700" stop="20210912204500 +0700" channel="vtvcab7">
    <title lang="vi">Camera On 1209 Bất chấp nhận đồ từ thiện (Mới SX)</title>
  </programme>
  <programme start="20210912204500 +0700" stop="20210912210000 +0700" channel="vtvcab7">
    <title lang="vi">Công Sở Truyền Kỳ (210) 63</title>
  </programme>
  <programme start="20210912210000 +0700" stop="20210912220000 +0700" channel="vtvcab7">
    <title lang="vi">Dj Star 2020 5</title>
  </programme>
  <programme start="20210912220000 +0700" stop="20210912224500 +0700" channel="vtvcab7">
    <title lang="vi">Phim Truyện (Pl 17H) Sông dài (39)</title>
  </programme>
  <programme start="20210912224500 +0700" stop="20210912230000 +0700" channel="vtvcab7">
    <title lang="vi">Sk&amp;Cs 24/7 12/09/2021 12:00:00 SA</title>
  </programme>
  <programme start="20210912230000 +0700" stop="20210912233000 +0700" channel="vtvcab7">
    <title lang="vi">Truy Vết 1209 Củ Bình Vôi trên núi cao (Mới SX)</title>
  </programme>
  <programme start="20210912233000 +0700" stop="20210912234500 +0700" channel="vtvcab7">
    <title lang="vi">Cảnh Báo Từ Cuộc Sống 1109 Trầm cảm nhân đôi vì mạng xã hội</title>
  </programme>
  <programme start="20210912000000 +0700" stop="20210912003000 +0700" channel="vtvcab8">
    <title lang="vi">Sam siêu đẳng T7</title>
  </programme>
  <programme start="20210912003000 +0700" stop="20210912010000 +0700" channel="vtvcab8">
    <title lang="vi">Stella và Sam T4</title>
  </programme>
  <programme start="20210912010000 +0700" stop="20210912013000 +0700" channel="vtvcab8">
    <title lang="vi">Nghìn lẻ một đêm T3</title>
  </programme>
  <programme start="20210912013000 +0700" stop="20210912020000 +0700" channel="vtvcab8">
    <title lang="vi">Siêu nhân Max Steel T23</title>
  </programme>
  <programme start="20210912020000 +0700" stop="20210912023000 +0700" channel="vtvcab8">
    <title lang="vi">Hai cây khế (8&amp;#39;) + Công chúa bán than ( 11&amp;#39;)</title>
  </programme>
  <programme start="20210912023000 +0700" stop="20210912030000 +0700" channel="vtvcab8">
    <title lang="vi">Nghìn lẻ một đêm T4</title>
  </programme>
  <programme start="20210912030000 +0700" stop="20210912033000 +0700" channel="vtvcab8">
    <title lang="vi">Stella và Sam T5</title>
  </programme>
  <programme start="20210912033000 +0700" stop="20210912040000 +0700" channel="vtvcab8">
    <title lang="vi">Bước nhảy cuồng nhiệt Số 9</title>
  </programme>
  <programme start="20210912040000 +0700" stop="20210912043000 +0700" channel="vtvcab8">
    <title lang="vi">Sam siêu đẳng T9</title>
  </programme>
  <programme start="20210912043000 +0700" stop="20210912050000 +0700" channel="vtvcab8">
    <title lang="vi">Siêu nhân Max Steel T24</title>
  </programme>
  <programme start="20210912050000 +0700" stop="20210912053000 +0700" channel="vtvcab8">
    <title lang="vi">Đứa con vàng (10&amp;#39;) + Hoàng tử không biết sợ (11&amp;#39;)</title>
  </programme>
  <programme start="20210912053000 +0700" stop="20210912060000 +0700" channel="vtvcab8">
    <title lang="vi">Stella và Sam T6</title>
  </programme>
  <programme start="20210912060000 +0700" stop="20210912063000 +0700" channel="vtvcab8">
    <title lang="vi">Ca nhạc Doremi Số 4</title>
  </programme>
  <programme start="20210912063000 +0700" stop="20210912070000 +0700" channel="vtvcab8">
    <title lang="vi">Con yêu ơi đừng sợ Số 78</title>
  </programme>
  <programme start="20210912070000 +0700" stop="20210912073000 +0700" channel="vtvcab8">
    <title lang="vi">Sam siêu đẳng T10</title>
  </programme>
  <programme start="20210912073000 +0700" stop="20210912080000 +0700" channel="vtvcab8">
    <title lang="vi">Siêu nhân Max Steel T25</title>
  </programme>
  <programme start="20210912080000 +0700" stop="20210912083000 +0700" channel="vtvcab8">
    <title lang="vi">Stella và Sam T7</title>
  </programme>
  <programme start="20210912083000 +0700" stop="20210912090000 +0700" channel="vtvcab8">
    <title lang="vi">Nghìn lẻ một đêm T5</title>
  </programme>
  <programme start="20210912090000 +0700" stop="20210912093000 +0700" channel="vtvcab8">
    <title lang="vi">Tình yêu của muối (11&amp;#39;) + Alibaba và bốn mươi tên cướp (11&amp;#39;)</title>
  </programme>
  <programme start="20210912093000 +0700" stop="20210912100000 +0700" channel="vtvcab8">
    <title lang="vi">Sam siêu đẳng T11</title>
  </programme>
  <programme start="20210912100000 +0700" stop="20210912103000 +0700" channel="vtvcab8">
    <title lang="vi">Bước nhảy cuồng nhiệt Số 10</title>
  </programme>
  <programme start="20210912103000 +0700" stop="20210912110000 +0700" channel="vtvcab8">
    <title lang="vi">Stella và Sam T8</title>
  </programme>
  <programme start="20210912110000 +0700" stop="20210912113000 +0700" channel="vtvcab8">
    <title lang="vi">Ca nhạc Doremi Số 5</title>
  </programme>
  <programme start="20210912113000 +0700" stop="20210912120000 +0700" channel="vtvcab8">
    <title lang="vi">Sam siêu đẳng T12</title>
  </programme>
  <programme start="20210912120000 +0700" stop="20210912123000 +0700" channel="vtvcab8">
    <title lang="vi">Siêu nhân Max Steel T26</title>
  </programme>
  <programme start="20210912123000 +0700" stop="20210912130000 +0700" channel="vtvcab8">
    <title lang="vi">Nghìn lẻ một đêm T6</title>
  </programme>
  <programme start="20210912130000 +0700" stop="20210912133000 +0700" channel="vtvcab8">
    <title lang="vi">Ba hạt hồ đào (18&amp;#39;)</title>
  </programme>
  <programme start="20210912133000 +0700" stop="20210912140000 +0700" channel="vtvcab8">
    <title lang="vi">Sam siêu đẳng T13</title>
  </programme>
  <programme start="20210912140000 +0700" stop="20210912143000 +0700" channel="vtvcab8">
    <title lang="vi">Ca nhạc Doremi Số 6</title>
  </programme>
  <programme start="20210912143000 +0700" stop="20210912150000 +0700" channel="vtvcab8">
    <title lang="vi">Siêu nhân Max Steel T27</title>
  </programme>
  <programme start="20210912150000 +0700" stop="20210912153000 +0700" channel="vtvcab8">
    <title lang="vi">Nghìn lẻ một đêm T7</title>
  </programme>
  <programme start="20210912153000 +0700" stop="20210912160000 +0700" channel="vtvcab8">
    <title lang="vi">ONKids tiểu phẩm Số 71</title>
  </programme>
  <programme start="20210912160000 +0700" stop="20210912163000 +0700" channel="vtvcab8">
    <title lang="vi">Sam siêu đẳng T14</title>
  </programme>
  <programme start="20210912163000 +0700" stop="20210912170000 +0700" channel="vtvcab8">
    <title lang="vi">Stella và Sam T9</title>
  </programme>
  <programme start="20210912170000 +0700" stop="20210912173000 +0700" channel="vtvcab8">
    <title lang="vi">Siêu nhân Max Steel T28</title>
  </programme>
  <programme start="20210912173000 +0700" stop="20210912180000 +0700" channel="vtvcab8">
    <title lang="vi">Khám phá thế giới cùng Thomas và những người bạn T14</title>
  </programme>
  <programme start="20210912180000 +0700" stop="20210912183000 +0700" channel="vtvcab8">
    <title lang="vi">Một đòn chết bảy (18&amp;#39;)</title>
  </programme>
  <programme start="20210912183000 +0700" stop="20210912190000 +0700" channel="vtvcab8">
    <title lang="vi">Vòng xoay thần tốc T6</title>
  </programme>
  <programme start="20210912190000 +0700" stop="20210912193000 +0700" channel="vtvcab8">
    <title lang="vi">Chiến vương nắp chai T6( 11&amp;#39;) + Lego Ninjago - Thuỷ chiến đáy đại dương T18</title>
  </programme>
  <programme start="20210912193000 +0700" stop="20210912200000 +0700" channel="vtvcab8">
    <title lang="vi">Nghìn lẻ một đêm T8</title>
  </programme>
  <programme start="20210912200000 +0700" stop="20210912202500 +0700" channel="vtvcab8">
    <title lang="vi">ONKids tiểu phẩm Số 72</title>
  </programme>
  <programme start="20210912202500 +0700" stop="20210912203000 +0700" channel="vtvcab8">
    <title lang="vi">Tôi kể bạn nghe Nói dối như cuội P2</title>
  </programme>
  <programme start="20210912203000 +0700" stop="20210912210000 +0700" channel="vtvcab8">
    <title lang="vi">Ca nhạc Doremi Số 7</title>
  </programme>
  <programme start="20210912210000 +0700" stop="20210912211000 +0700" channel="vtvcab8">
    <title lang="vi">Câu chuyện trước khi đi ngủ Củ cà rốt di động</title>
  </programme>
  <programme start="20210912211000 +0700" stop="20210912213000 +0700" channel="vtvcab8">
    <title lang="vi">Sam siêu đẳng T15</title>
  </programme>
  <programme start="20210912213000 +0700" stop="20210912220000 +0700" channel="vtvcab8">
    <title lang="vi">ONKids tiểu phẩm Số 71</title>
  </programme>
  <programme start="20210912220000 +0700" stop="20210912223000 +0700" channel="vtvcab8">
    <title lang="vi">Siêu nhân Max Steel T27</title>
  </programme>
  <programme start="20210912223000 +0700" stop="20210912230000 +0700" channel="vtvcab8">
    <title lang="vi">Nghìn lẻ một đêm T7</title>
  </programme>
  <programme start="20210912230000 +0700" stop="20210912233000 +0700" channel="vtvcab8">
    <title lang="vi">Stella và Sam T8</title>
  </programme>
  <programme start="20210912000500 +0700" stop="20210912010500 +0700" channel="vtvcab9">
    <title lang="vi">Phim Cục Cưng Rắc Rối (60 Tập) Hàn Quốc - Tập 49 Phát Lại</title>
  </programme>
  <programme start="20210912010500 +0700" stop="20210912013500 +0700" channel="vtvcab9">
    <title lang="vi">Báo Chí Góc Nhìn 2021 - Số 36 Phát Lại</title>
  </programme>
  <programme start="20210912013500 +0700" stop="20210912020500 +0700" channel="vtvcab9">
    <title lang="vi">Tài Chính Thông Minh 2021 - Số 36 Phát Lại</title>
  </programme>
  <programme start="20210912020500 +0700" stop="20210912030500 +0700" channel="vtvcab9">
    <title lang="vi">Phim Ngọt Ngào Tình Cha (74 Tập) Đài Loan - Tập 49 Phát Lại</title>
  </programme>
  <programme start="20210912030500 +0700" stop="20210912031000 +0700" channel="vtvcab9">
    <title lang="vi">Kí Sự Khám Phá 2021 - Số 215 Phát Lại</title>
  </programme>
  <programme start="20210912031000 +0700" stop="20210912033500 +0700" channel="vtvcab9">
    <title lang="vi">Sitcom Xóm Trọ Thanh Xuân 2021 - Số 102 Phát Lại</title>
  </programme>
  <programme start="20210912033500 +0700" stop="20210912040500 +0700" channel="vtvcab9">
    <title lang="vi">Báo Chí Góc Nhìn 2021 - Số 36 Phát Lại</title>
  </programme>
  <programme start="20210912040500 +0700" stop="20210912043500 +0700" channel="vtvcab9">
    <title lang="vi">Thế Giới 23 Độ 5 2021 - Số 36 Phát Lại</title>
  </programme>
  <programme start="20210912043500 +0700" stop="20210912050500 +0700" channel="vtvcab9">
    <title lang="vi">Tài Chính Thông Minh 2021 - Số 36 Phát Lại</title>
  </programme>
  <programme start="20210912050500 +0700" stop="20210912060000 +0700" channel="vtvcab9">
    <title lang="vi">Phim Cục Cưng Rắc Rối (60 Tập) Hàn Quốc - Tập 49 Phát Lại</title>
  </programme>
  <programme start="20210912060000 +0700" stop="20210912061000 +0700" channel="vtvcab9">
    <title lang="vi">Thế Giới 23 Độ 5 2021 - Số 36 Phát Lại - Phần 1</title>
  </programme>
  <programme start="20210912061000 +0700" stop="20210912062000 +0700" channel="vtvcab9">
    <title lang="vi">Thế Giới 23 Độ 5 2021 - Số 36 Phát Lại - Phần 2</title>
  </programme>
  <programme start="20210912062000 +0700" stop="20210912063500 +0700" channel="vtvcab9">
    <title lang="vi">Thế Giới 23 Độ 5 2021 - Số 36 Phát Lạil - Phần 3</title>
  </programme>
  <programme start="20210912063500 +0700" stop="20210912064500 +0700" channel="vtvcab9">
    <title lang="vi">Dạy Golf 2021 - Số 251 Phát Mới</title>
  </programme>
  <programme start="20210912064500 +0700" stop="20210912070500 +0700" channel="vtvcab9">
    <title lang="vi">Sitcom Công Sở Truyền Kỳ 2021 - Số 143 Phát Lại</title>
  </programme>
  <programme start="20210912070500 +0700" stop="20210912073500 +0700" channel="vtvcab9">
    <title lang="vi">Tài Chính Thông Minh 2021 - Số 36 Phát Lại</title>
  </programme>
  <programme start="20210912073500 +0700" stop="20210912080500 +0700" channel="vtvcab9">
    <title lang="vi">Báo Chí Góc Nhìn 2021 - Số 36 Phát Lại</title>
  </programme>
  <programme start="20210912080500 +0700" stop="20210912083500 +0700" channel="vtvcab9">
    <title lang="vi">Thế Giới 23 Độ 5 2021 - Số 36 Phát Lại</title>
  </programme>
  <programme start="20210912083500 +0700" stop="20210912090500 +0700" channel="vtvcab9">
    <title lang="vi">Tài Chính Thông Minh 2021 - Số 36 Phát Lại</title>
  </programme>
  <programme start="20210912090500 +0700" stop="20210912100500 +0700" channel="vtvcab9">
    <title lang="vi">Phim Khép Lại Quá Khứ (32 Tập) - Tập 13 Phát Lại</title>
  </programme>
  <programme start="20210912100500 +0700" stop="20210912101000 +0700" channel="vtvcab9">
    <title lang="vi">Kí Sự Khám Phá 2021 - Số 193 Phát Lại</title>
  </programme>
  <programme start="20210912101000 +0700" stop="20210912103500 +0700" channel="vtvcab9">
    <title lang="vi">Sitcom Xóm Trọ Thanh Xuân 2021 - Số 100 Phát Lại</title>
  </programme>
  <programme start="20210912103500 +0700" stop="20210912110000 +0700" channel="vtvcab9">
    <title lang="vi">Báo Chí Góc Nhìn 2021 - Số 36 Phát Lại</title>
  </programme>
  <programme start="20210912110000 +0700" stop="20210912120500 +0700" channel="vtvcab9">
    <title lang="vi">Phim Sự Trả Thù Ngọt Ngào (Tq 83 Tập) - Tập 8 Phát Mới</title>
  </programme>
  <programme start="20210912120500 +0700" stop="20210912134000 +0700" channel="vtvcab9">
    <title lang="vi">Hài Dân Gian 19h50.2021 - Số 38 Phát Lại</title>
  </programme>
  <programme start="20210912134000 +0700" stop="20210912134500 +0700" channel="vtvcab9">
    <title lang="vi">Báo Chí Góc Nhìn 2021 - Số 36 Phát Lại</title>
  </programme>
  <programme start="20210912134500 +0700" stop="20210912140500 +0700" channel="vtvcab9">
    <title lang="vi">Sitcom Công Sở Truyền Kỳ 2021 - Số 23 Phát Lại</title>
  </programme>
  <programme start="20210912140500 +0700" stop="20210912143500 +0700" channel="vtvcab9">
    <title lang="vi">Thế Giới 23 Độ 5 2021 - Số 36 Phát Lại</title>
  </programme>
  <programme start="20210912143500 +0700" stop="20210912150500 +0700" channel="vtvcab9">
    <title lang="vi">Báo Chí Góc Nhìn 2021 - Số 36 Phát Lại</title>
  </programme>
  <programme start="20210912150500 +0700" stop="20210912151500 +0700" channel="vtvcab9">
    <title lang="vi">Sitcom 2021 Soái Ca Anh Ở Đâu (150 Tập) - Số 68 Phát Lại</title>
  </programme>
  <programme start="20210912151500 +0700" stop="20210912153500 +0700" channel="vtvcab9">
    <title lang="vi">Dạy Golf 2021 - Số 251 Phát Lại</title>
  </programme>
  <programme start="20210912153500 +0700" stop="20210912160500 +0700" channel="vtvcab9">
    <title lang="vi">Tài Chính Thông Minh 2021 - Số 36 Phát Lại</title>
  </programme>
  <programme start="20210912160500 +0700" stop="20210912161000 +0700" channel="vtvcab9">
    <title lang="vi">Kí Sự Khám Phá 2021 - Số 250 Phát Lại</title>
  </programme>
  <programme start="20210912161000 +0700" stop="20210912163500 +0700" channel="vtvcab9">
    <title lang="vi">Dạy Golf 2021 - Số 251 Phát Lại</title>
  </programme>
  <programme start="20210912163500 +0700" stop="20210912171000 +0700" channel="vtvcab9">
    <title lang="vi">Tài Chính Thông Minh 2021 - Số 36 Phát Lại</title>
  </programme>
  <programme start="20210912171000 +0700" stop="20210912173500 +0700" channel="vtvcab9">
    <title lang="vi">Thế Giới 23 Độ 5 2021 - Số 36 Phát Lại</title>
  </programme>
  <programme start="20210912173500 +0700" stop="20210912174500 +0700" channel="vtvcab9">
    <title lang="vi">Hoạt Hình 2021 - Số 236 Phát Mới</title>
  </programme>
  <programme start="20210912174500 +0700" stop="20210912181500 +0700" channel="vtvcab9">
    <title lang="vi">Kí Sự Khám Phá 2021 - Số 245 Phát Mới</title>
  </programme>
  <programme start="20210912181500 +0700" stop="20210912190500 +0700" channel="vtvcab9">
    <title lang="vi">Phim Khép Lại Quá Khứ (32 Tập) - Tập 14 Phát Mới</title>
  </programme>
  <programme start="20210912190500 +0700" stop="20210912191000 +0700" channel="vtvcab9">
    <title lang="vi">Sitcom Xóm Trọ Thanh Xuân 2021 - Số 108 Phát Mới</title>
  </programme>
  <programme start="20210912191000 +0700" stop="20210912191500 +0700" channel="vtvcab9">
    <title lang="vi">Thế Giới 23 Độ 5 2021 - Số 36 Phát Lại</title>
  </programme>
  <programme start="20210912191500 +0700" stop="20210912203000 +0700" channel="vtvcab9">
    <title lang="vi">Hài Dân Gian 19h50.2021 - Số 38 Phát Mới</title>
  </programme>
  <programme start="20210912203000 +0700" stop="20210912213000 +0700" channel="vtvcab9">
    <title lang="vi">Dạy Golf 2021 - Số 37 Phát Lại</title>
  </programme>
  <programme start="20210912213000 +0700" stop="20210912214000 +0700" channel="vtvcab9">
    <title lang="vi">Phim Sự Trả Thù Câm Lặng Phát Mới</title>
  </programme>
  <programme start="20210912214000 +0700" stop="20210912222500 +0700" channel="vtvcab9">
    <title lang="vi">Thế Giới 23 Độ 5 2021 - Số 36 Phát Lại</title>
  </programme>
  <programme start="20210912222500 +0700" stop="20210912233500 +0700" channel="vtvcab9">
    <title lang="vi">Phim 90p Sau Tận Thế Phát Mới</title>
  </programme>
</tv>